gym_cap32/__init__.py
gym_cap32/envs/__init__.py
gym_cap32/envs/cap32_env.py
gym_cap32/envs/cap32_extrahard_env.py
gym_cap32/snap/arka.sna
gym_cap32/snap/buggy.sna
gym_cap32-1.0.9.dist-info/METADATA
gym_cap32-1.0.9.dist-info/WHEEL
gym_cap32-1.0.9.dist-info/top_level.txt
gym_cap32-1.0.9.dist-info/RECORD
