Metadata-Version: 2.1
Name: gym-cap32
Version: 1.0.9
Summary: Gym environment for Amstrad CPC.
Home-page: https://github.com/pypa/sampleproject
Author: Theo De castro Pinto, Wilfried Augeard
Author-email: decastrotheo960@gmail.com
License: UNKNOWN
Platform: UNKNOWN
Classifier: Programming Language :: Python :: 3
Classifier: License :: OSI Approved :: MIT License
Classifier: Operating System :: OS Independent
Requires-Python: >=3.6
